{
    "version": "1",
    "name": "became rush moon",
    "description": "ocean spring each person practical special local voyage human nest none forth open choose visitor whistle grandfather took rate property label willing stood enough record thee constantly no nearest form willing member that usual gasoline unhappy truth continent lonely scale only art empty business case eye they married exclaimed taste floating natural industry after gentle direction orange sound according thee them glad in realize cat yet thumb largest reason oxygen suppose prevent peace fruit bring talk soil already fewer score essential phrase show hay twice morning stepped trunk just stiff zipper common call garage clearly enjoy gun steel widely union orange engineer nothing fly frog rapidly require flight charge picture call drove tongue dollar electricity himself cell lay search trail judge time stuck copper dug thou gas control vote secret master good railroad might roof burn missing gradually spirit ever printed him held cut shorter die equipment verb very proud original prepare ordinary joined many thrown cow trace meet except curve using properly coffee eye like wonder failed easily wind uncle sound enter using lift level office driven alike model flight zipper laugh setting cover atom queen grain stared felt customs joined love success hat older furniture you grain sort",
    "image": "ipfs://QmaCA2KUUKpbjYcC6NuTNqgnx4RYP1DPx7fWUEz1TSUsVB/34.png",
    "attributes": [ null ],
    "properties": {
    "collection": "testColleciton",
    "collectionId": "testColleciton",
    "total_supply": "200",
    "external_url": "This can be cloudinary url",
    "animation_url": null
    },
    "localization": {
    "uri": null,
    "locales": [
    "en"
    ],
    "default": "en"
    }
    }